youtube_url_parser/__init__.py
youtube_url_parser/parser.py
youtube_url_parser-0.1.0.dist-info/licenses/LICENSE
youtube_url_parser-0.1.0.dist-info/METADATA
youtube_url_parser-0.1.0.dist-info/WHEEL
youtube_url_parser-0.1.0.dist-info/top_level.txt
youtube_url_parser-0.1.0.dist-info/RECORD
