Metadata-Version: 2.4
Name: youtube_url_parser
Version: 0.1.0
Summary: Extract YouTube video IDs from various URL formats
Author-email: Roman <youtube-url-parser@romantaylor.com>
License-Expression: MIT
Requires-Python: >=3.8
License-File: LICENSE
Dynamic: license-file
